{
    "errormsg": false,
    "totals": 52,
    "curr_page": 1,
    "pages": 3,
    "record": [
        {
            "id": "12357",
            "title": "互联网+的古惑仔时代3",
            "grade": "30",
            "classes": "钻石会员",
            "image": "http://i1.umivi.net/v/album/listimage/2016-05/12357_190X1420525.jpg",
            "authorname": "傅彦生 管家帮创始人、董事长  ",
            "detailurl": "http://i.v.youmi.cn/ClientApi/getAlbumDetail?id=12357&frm=fromCategoryOrTutorGetAlbumList",
            "watchnum": "430"
        },
        {
            "id": "12354",
            "title": " 互联网+的古惑仔时代2",
            "grade": "30",
            "classes": "钻石会员",
            "image": "http://i1.umivi.net/v/album/listimage/2016-05/12354_190X1420523.jpg",
            "authorname": "傅彦生 管家帮创始人、董事长  ",
            "detailurl": "http://i.v.youmi.cn/ClientApi/getAlbumDetail?id=12354&frm=fromCategoryOrTutorGetAlbumList",
            "watchnum": "240"
        },
        {
            "id": "12352",
            "title": "互联网+的古惑仔时代1",
            "grade": "30",
            "classes": "钻石会员",
            "image": "http://i1.umivi.net/v/album/listimage/2016-05/12352_190X1420524.jpg",
            "authorname": "傅彦生 管家帮创始人、董事长  ",
            "detailurl": "http://i.v.youmi.cn/ClientApi/getAlbumDetail?id=12352&frm=fromCategoryOrTutorGetAlbumList",
            "watchnum": "330"
        },
        {
            "id": "12319",
            "title": "饿了么30亿美元估值背后",
            "grade": "30",
            "classes": "钻石会员",
            "image": "http://i1.umivi.net/v/album/listimage/2016-04/12319_190X1420404.jpg",
            "authorname": "查立 乾龙创投创始合伙人   ",
            "detailurl": "http://i.v.youmi.cn/ClientApi/getAlbumDetail?id=12319&frm=fromCategoryOrTutorGetAlbumList",
            "watchnum": "2951"
        },
        {
            "id": "12270",
            "title": "传统企业如何转互联网+？",
            "grade": "30",
            "classes": "钻石会员",
            "image": "http://i1.umivi.net/v/album/listimage/2015-11/12270_190X1421127.jpg",
            "authorname": "文杰 大家社区 CEO",
            "detailurl": "http://i.v.youmi.cn/ClientApi/getAlbumDetail?id=12270&frm=fromCategoryOrTutorGetAlbumList",
            "watchnum": "3880"
        },
        {
            "id": "12266",
            "title": "用连锁的规律打造超级品牌",
            "grade": "30",
            "classes": "钻石会员",
            "image": "http://i1.umivi.net/v/album/listimage/2015-11/12266_190X1421124.jpg",
            "authorname": "铁丁 元一连锁品牌策略机构创始人",
            "detailurl": "http://i.v.youmi.cn/ClientApi/getAlbumDetail?id=12266&frm=fromCategoryOrTutorGetAlbumList",
            "watchnum": "2901"
        },
        {
            "id": "12241",
            "title": "按摩O2O寒冬中存活的条件",
            "grade": "30",
            "classes": "钻石会员",
            "image": "http://i1.umivi.net/v/album/listimage/2015-10/12241_190X1421028.jpg",
            "authorname": "于飞  宜生到家CEO",
            "detailurl": "http://i.v.youmi.cn/ClientApi/getAlbumDetail?id=12241&frm=fromCategoryOrTutorGetAlbumList",
            "watchnum": "2449"
        },
        {
            "id": "12209",
            "title": "将互联网家装极致化",
            "grade": "1",
            "classes": "精品课程",
            "image": "http://i1.umivi.net/v/album/listimage/2015-09/12209_190X1420917.jpg",
            "authorname": "陈炜 爱空间创始人",
            "detailurl": "http://i.v.youmi.cn/ClientApi/getAlbumDetail?id=12209&frm=fromCategoryOrTutorGetAlbumList",
            "watchnum": "12239"
        },
        {
            "id": "12188",
            "title": "将互+跨境进行到底",
            "grade": "30",
            "classes": "钻石会员",
            "image": "http://i1.umivi.net/v/album/listimage/2015-08/12188_190X1420814.jpg",
            "authorname": "周岚 阿里巴巴集团跨境B2C事业部副总经理",
            "detailurl": "http://i.v.youmi.cn/ClientApi/getAlbumDetail?id=12188&frm=fromCategoryOrTutorGetAlbumList",
            "watchnum": "3701"
        },
        {
            "id": "12176",
            "title": "高红冰王利芬点评互联网+云服务",
            "grade": "30",
            "classes": "钻石会员",
            "image": "http://i1.umivi.net/v/album/listimage/2015-08/12176_190X1420813.jpg",
            "authorname": "赵大伟 和君咨询集团合伙人    ",
            "detailurl": "http://i.v.youmi.cn/ClientApi/getAlbumDetail?id=12176&frm=fromCategoryOrTutorGetAlbumList",
            "watchnum": "1805"
        },
        {
            "id": "12168",
            "title": "UCloud云计算",
            "grade": "30",
            "classes": "钻石会员",
            "image": "http://i1.umivi.net/v/album/listimage/2015-08/12168_190X1420812.jpg",
            "authorname": "华琨 UCloud联合创始人兼COO",
            "detailurl": "http://i.v.youmi.cn/ClientApi/getAlbumDetail?id=12168&frm=fromCategoryOrTutorGetAlbumList",
            "watchnum": "500"
        },
        {
            "id": "12159",
            "title": "用互联网思维做汽修",
            "grade": "30",
            "classes": "钻石会员",
            "image": "http://i1.umivi.net/v/album/listimage/2015-08/12159_190X1420804.jpg",
            "authorname": "王正坤 易快修创始人兼CEO",
            "detailurl": "http://i.v.youmi.cn/ClientApi/getAlbumDetail?id=12159&frm=fromCategoryOrTutorGetAlbumList",
            "watchnum": "1915"
        },
        {
            "id": "12119",
            "title": "滴滴“流氓”地打败我",
            "grade": "30",
            "classes": "钻石会员",
            "image": "http://i1.umivi.net/v/album/listimage/2015-07/12119_190X1420707.jpg",
            "authorname": "孙志刚 红包易创始人  ",
            "detailurl": "http://i.v.youmi.cn/ClientApi/getAlbumDetail?id=12119&frm=fromCategoryOrTutorGetAlbumList",
            "watchnum": "2102"
        },
        {
            "id": "12091",
            "title": "互联网+旅游=？",
            "grade": "30",
            "classes": "钻石会员",
            "image": "http://i1.umivi.net/v/album/listimage/2015-06/12091_190X1420612.jpg",
            "authorname": "陈晓峰 嫁拍婚纱CEO    ",
            "detailurl": "http://i.v.youmi.cn/ClientApi/getAlbumDetail?id=12091&frm=fromCategoryOrTutorGetAlbumList",
            "watchnum": "3467"
        },
        {
            "id": "12090",
            "title": "风口下的生活服务",
            "grade": "30",
            "classes": "钻石会员",
            "image": "http://i1.umivi.net/v/album/listimage/2015-06/12090_190X1420609.jpg",
            "authorname": "唐万里 回家吃饭CEO，原阿里巴巴区域经理",
            "detailurl": "http://i.v.youmi.cn/ClientApi/getAlbumDetail?id=12090&frm=fromCategoryOrTutorGetAlbumList",
            "watchnum": "6501"
        },
        {
            "id": "12089",
            "title": "创业者的互联网+出行",
            "grade": "30",
            "classes": "钻石会员",
            "image": "http://i1.umivi.net/v/album/listimage/2015-06/12089_190X1420610.jpg",
            "authorname": "门旭光 51用车联合创始人兼CPO，曾任百度产品经理",
            "detailurl": "http://i.v.youmi.cn/ClientApi/getAlbumDetail?id=12089&frm=fromCategoryOrTutorGetAlbumList",
            "watchnum": "4513"
        },
        {
            "id": "12085",
            "title": "掌上药店如何做移动医疗",
            "grade": "30",
            "classes": "钻石会员",
            "image": "http://i1.umivi.net/v/album/listimage/2015-06/12085_190X1420619.jpg",
            "authorname": "王浚海 掌上药店创始人",
            "detailurl": "http://i.v.youmi.cn/ClientApi/getAlbumDetail?id=12085&frm=fromCategoryOrTutorGetAlbumList",
            "watchnum": "1492"
        },
        {
            "id": "11540",
            "title": "淘点点对O2O的理解和思考",
            "grade": "30",
            "classes": "钻石会员",
            "image": "http://i1.umivi.net/v/album/listimage/2014-09/11540_190X1420904.jpg",
            "authorname": "王煜磊 阿里巴巴集团副总裁 ",
            "detailurl": "http://i.v.youmi.cn/ClientApi/getAlbumDetail?id=11540&frm=fromCategoryOrTutorGetAlbumList",
            "watchnum": "4690"
        },
        {
            "id": "12080",
            "title": "生鲜O2O要这么玩才有未来",
            "grade": "30",
            "classes": "钻石会员",
            "image": "http://i1.umivi.net/v/album/listimage/2015-06/12080_190X1420602.jpg",
            "authorname": "丁景涛 邻和网创始人  ",
            "detailurl": "http://i.v.youmi.cn/ClientApi/getAlbumDetail?id=12080&frm=fromCategoryOrTutorGetAlbumList",
            "watchnum": "5858"
        },
        {
            "id": "11659",
            "title": "滴滴打车：O2O要做好三件事",
            "grade": "30",
            "classes": "钻石会员",
            "image": "http://i1.umivi.net/v/album/listimage/2015-05/11659_190X1420525.png",
            "authorname": "张博 滴滴打车联合创始人兼产品技术副总裁  ",
            "detailurl": "http://i.v.youmi.cn/ClientApi/getAlbumDetail?id=11659&frm=fromCategoryOrTutorGetAlbumList",
            "watchnum": "4145"
        }
    ],
    "returnmsg": "",
    "total": 20
}